trm/utils/__init__.py
trm/utils/core.py
trm/utils/vec3.py
trm.utils-1.0.0.dist-info/METADATA
trm.utils-1.0.0.dist-info/WHEEL
trm.utils-1.0.0.dist-info/top_level.txt
trm.utils-1.0.0.dist-info/RECORD
