Metadata-Version: 2.1
Name: trm.utils
Version: 1.0.0
Summary: Python utility classes and functions
Home-page: https://github.com/trmrsh/trm-utils
Author: Tom Marsh
Author-email: Tom Marsh <t.r.marsh@warwick.ac.uk>
License: BSD 3-Clause License
Project-URL: Homepage, https://github.com/trmrsh/trm-utils
Project-URL: Bug Tracker, https://github.com/trmrsh/trm-utils/issues
Classifier: Programming Language :: Python :: 3
Classifier: License :: OSI Approved :: BSD License
Requires-Python: >=3.6
Requires-Dist: astropy
Requires-Dist: numpy
Requires-Dist: scipy
